ai_creature_lang/__init__.py
ai_creature_lang/__main__.py
ai_creature_lang/ChatAiNpc.py
ai_creature_lang/InferServer.py
ai_creature_lang/Knowledge.py
ai_creature_lang/knowledge.txt
ai_creature_lang/Language.py
ai_creature_lang/pyarmor_runtime_000000/__init__.py
ai_creature_lang/pyarmor_runtime_000000/py310/pyarmor_runtime.so
ai_creature_lang/pyarmor_runtime_000000/py311/pyarmor_runtime.so
ai_creature_lang/pyarmor_runtime_000000/py312/pyarmor_runtime.so
ai_creature_lang/pyarmor_runtime_000000/py313/pyarmor_runtime.so
ai_creature_lang/Utils.py
ai_creature_lang/VoiceRecorder.py
ai_creature_lang-5.3.0.dist-info/entry_points.txt
ai_creature_lang-5.3.0.dist-info/METADATA
ai_creature_lang-5.3.0.dist-info/WHEEL
ai_creature_lang-5.3.0.dist-info/RECORD
