Metadata-Version: 2.3
Name: ai-creature-lang
Version: 5.3.0
Summary: AI chat in-game. Supports Don't Starve Together.
Author: Weire
Requires-Python: >=3.10,<3.14
Classifier: Operating System :: POSIX :: Linux
Classifier: Programming Language :: Python :: 3
Classifier: Programming Language :: Python :: 3.10
Classifier: Programming Language :: Python :: 3.11
Classifier: Programming Language :: Python :: 3.12
Classifier: Programming Language :: Python :: 3.13
Requires-Dist: flask (>=3.1.1,<4.0.0)
Requires-Dist: numpy (>=1.26.4,<2.0.0)
Requires-Dist: ollama (>=0.5.1,<0.6.0)
Requires-Dist: pynput (>=1.8.1,<2.0.0)
Requires-Dist: requests (>=2.32.4,<3.0.0)
Requires-Dist: scipy (>=1.15.3,<2.0.0)
Requires-Dist: sounddevice (>=0.5.2,<0.6.0)
